convstruct/__init__.py
convstruct/api/__init__.py
convstruct/api/core.py
convstruct/api/ops.py
convstruct/api/util.py
convstruct/evaluator/__init__.py
convstruct-1.1.0.dist-info/METADATA
convstruct-1.1.0.dist-info/WHEEL
convstruct-1.1.0.dist-info/top_level.txt
convstruct-1.1.0.dist-info/RECORD
