Metadata-Version: 2.1
Name: convstruct
Version: 1.1.0
Summary: NAS + RL
Home-page: UNKNOWN
Author: convstruct
Author-email: hello@convstruct.org
License: Apache Licence 2.0
Platform: UNKNOWN
Classifier: Programming Language :: Python :: 3.6
Requires-Python: ==3.6.8
